{
  "dates": {

    "2026-04-10": {
      "schedule": [
        {
          "time": "1:00",
          "text": "晚安蔡蓁蓁💤 明天早上要去當兵了🪖"
        },
        {
          "time": "11:00",
          "text": "早安蔡蓁蓁🌞 今天是當兵的第一天喔 現在應該在火車上🚂"
        },
        {
          "time": "18:00",
          "text": "不知道你現在是不是在讀書 讀很累的話休息一下準備吃晚餐了喔 辛苦你了🫂"
        },
        {
          "time": "20:00",
          "type": "memory",
          "image_id": "1bCZaCWJ6Cr0FAc5Suhu94kIsOm9vsPpE",
          "text": "爬完合歡山⛰ 我睡死了被你偷拍 好久以前了喔"
        },
        {
          "time": "23:59",
          "text": "蓁 晚安🌙 明天 kpop summit 加油喔！ 下禮拜再來看你表演的影片🍿"
        }
      ]
    },

    "2026-04-11": {
      "schedule": [
        {
          "time": "10:00",
          "text": "蓁早安唷～ 應該在準備去表演了吧 出門要注意安全喔 祝你表演順利💃"
        },
        {
          "time": "18:00",
          "text": "應該表演完了吧 跳完舞可以多吃一點了 吃點好吃的開心一下😋"
        },
        {
          "time": "23:59",
          "text": "蓁 今天過得怎麼樣呢？ 傳個數字給我（1-10）"
        }
      ]
    },

    "2026-04-12": {
      "schedule": [
        {
          "time": "1:00",
          "text": "應該在滑手機吧 早點休息喔 明天應該要讀書了 繼續加油喔⛽️ 蓁晚安🌝"
        },
        {
          "time": "11:00",
          "text": "早安蔡蓁蓁🌞 今天是當兵第三天 不知道我有沒有辦法用手機傳訊息給你 讀書加油喔 我猜你今天都在讀書 但累了也要記得休息喔"
        },
        {
          "time": "18:00",
          "text": "今天推薦你一首歌 ... "
        },
        {
          "time": "23:59",
          "text": "今天讀很多書很棒了 要早點睡覺喔 明天還要去學校上課 辛苦你了 晚安喔蓁🌙"
        }
      ]
    },

    "2026-04-13": {
      "schedule": [
        {
          "time": "10:00",
          "text": "蔡安柏早安！ 今天是星期一 我這週結束就可以出來了 你也要加油喔💪\n出門要記得帶衛生棉喔 月經應該要來了"
        },
        {
          "time": "13:00",
          "text": "今天的課結束了 上課辛苦了喔 萬一不懂的話也沒關係 再花時間理解一下就懂了 加油蔡蓁蓁\n如果月經來不舒服的話就回家休息喔 也別太逞強"
        },
        {
          "time": "19:00",
          "text": "這幾天過得怎麼樣呢 我也進去當兵三天了 不知道拿到手機了沒😵 真想跟你講話"
        },
        {
          "time": "23:59",
          "text": "蔡蓁蓁 晚安🌙 今天過得怎麼樣呢？ 傳個數字給我（1-10）"
        }
      ]
    },

    "2026-04-14": {
      "schedule": [
        {
          "time": "1:00",
          "text": "今天去學校還有讀書 已經很努力了喔辛苦你了 早點休息喔 晚安喔蔡蓁蓁 祝你夢到我🌙"
        },
        {
          "time": "11:00",
          "text": "早安蓁😁 今天不知道你有沒有不舒服 不舒服的話就好好休息喔 等身體舒服一點了再讀"
        },
        {
          "time": "16:00",
          "type": "memory",
          "image_id": "1xdt9tgAPQSfHZ3jREMNgP-dKxFYjfiVD",
          "text": "晚上在圖書館一起讀書📚 好久以前了"
        },
        {
          "time": "23:59",
          "text": "蔡蓁蓁 晚安🌙 再過幾天就要出來了 快要可以用手機了 明天去上數學課別太有壓力喔 答不出來也不要緊張 你已經很棒了👍"
        }
      ]
    },

    "2026-04-15": {
      "schedule": [
        {
          "time": "10:00",
          "text": "早安蔡蓁蓁～ 有沒有睡好呢 今天是星期三 這週過一半了～"
        },
        {
          "time": "15:00",
          "text": "下課了～ 這禮拜的課都結束了辛苦你了 身體不舒服的話早點回家休息喔"
        },
        {
          "time": "20:00",
          "text": "今天推薦你一首歌 - 待定"
        },
        {
          "time": "23:59",
          "text": "蓁 晚安🌙 今天過得怎麼樣呢？ 傳個數字給我（1-10）"
        }
      ]
    },

    "2026-04-16": {
      "schedule": [
        {
          "time": "1:00",
          "text": "晚安蔡蓁蓁 早點休息喔 明天應該還要學後天要練的舞吧 明天也要繼續加油喔 但累了還是要放鬆一下👻"
        },
        {
          "time": "11:00",
          "text": "早安蓁🌤️ 今天是星期四 明天中午過後我就出來了 你今天也要加油喔 但也別太累了"
        },
        {
          "time": "18:00",
          "type": "memory",
          "image_id": "1Z2ltJzsSwuChSX8MRRACpPC0zXP8JTcM",
          "text": "第一次一起出去玩喔 是去 Xpark看魚🐟"
        },
        {
          "time": "23:59",
          "text": "明天就要出來了 但我知道你不一定有空你還要練舞 等你有空的時候再跟你分享發生什麼事喔 我也想知道你這禮拜過得怎麼樣 早點休息喔 蔡蓁蓁晚安🌙"
        }
      ]
    }

  }
}
